sweeper/__init__.py
sweeper/__main__.py
sweeper/address_parser.py
sweeper/backup.py
sweeper/config.py
sweeper/report.py
sweeper/street_types.json
sweeper/utilities.py
sweeper/workspace_info.py
sweeper/sweepers/UseLimitations.html
sweeper/sweepers/__init__.py
sweeper/sweepers/addresses.py
sweeper/sweepers/base.py
sweeper/sweepers/duplicates.py
sweeper/sweepers/empties.py
sweeper/sweepers/invalids.py
sweeper/sweepers/metadata.py
agrc_sweeper-2.0.0.dist-info/LICENSE
agrc_sweeper-2.0.0.dist-info/METADATA
agrc_sweeper-2.0.0.dist-info/WHEEL
agrc_sweeper-2.0.0.dist-info/entry_points.txt
agrc_sweeper-2.0.0.dist-info/top_level.txt
agrc_sweeper-2.0.0.dist-info/RECORD
