Metadata-Version: 2.1
Name: agrc-sweeper
Version: 2.0.0
Summary: CLI tool for making good data
Home-page: https://github.com/agrc/sweeper
Author: UGRC
Author-email: ugrc-developers@utah.gov
License: MIT
Platform: UNKNOWN
Classifier: Development Status :: 5 - Production/Stable
Classifier: Intended Audience :: Developers
Classifier: License :: OSI Approved :: MIT License
Classifier: Operating System :: Unix
Classifier: Operating System :: POSIX
Classifier: Operating System :: Microsoft :: Windows
Classifier: Programming Language :: Python
Classifier: Programming Language :: Python :: 3 :: Only
Classifier: Topic :: Utilities
Requires-Python: >=3
License-File: LICENSE
Requires-Dist: agrc-supervisor ==3.*
Requires-Dist: agrc-usaddress ==0.*
Requires-Dist: beautifulsoup4 ==4.*
Requires-Dist: docopt ==0.*
Requires-Dist: html5lib ==1.*
Requires-Dist: xxhash ==3.*
Provides-Extra: tests
Requires-Dist: pytest-cov ==5.* ; extra == 'tests'
Requires-Dist: pytest-instafail ==0.5.* ; extra == 'tests'
Requires-Dist: pytest-mock ==3.* ; extra == 'tests'
Requires-Dist: pytest-watch ==4.* ; extra == 'tests'
Requires-Dist: pytest ==8.* ; extra == 'tests'
Requires-Dist: ruff ==0.* ; extra == 'tests'
